{
  "name": "Chipotle Mexican Grill",
  "disclaimer": "Disclaaimer.",
  "customAllergens": [
    {"id": "gluten", "displayName": "Gluten"},
    {"id": "dairy", "displayName": "Dairy"},
    {"id": "soy", "displayName": "Soy"},
    {"id": "sulfites", "displayName": "Sulfites"},
    {"id": "mustard", "displayName": "Mustard"},
    {"id": "sulfites", "displayName": "Sulfites"},
    {"id": "sulfites", "displayName": "Sulfites"},
    {"id": "sulfites", "displayName": "Sulfites"},
    {"id": "sulfites", "displayName": "Sulfites"}
    
  ],
    "items": [
    {
      "name": "Chicken Burrito",
      "category": "Entrees",
      "allergens": [
        {"id": "gluten"},
        {"id": "dairy"}
      ]
    },
    {
      "name": "Veggie Bowl",
      "category": "Entrees",
      "allergens": []
    },
    {
      "name": "Chips & Guacamole",
      "category": "Sides",
      "allergens": [
        {"id": "sulfites"}
      ]
    }
  ]
}